.gitignore
.travis.yml
CONTRIBUTING.md
LICENSE
README.md
requirements-dev.txt
requirements.txt
setup.cfg
setup.py
examples/bar_example.ipynb
examples/barh_example.ipynb
examples/donut_example.ipynb
examples/line_example.ipynb
examples/pie_example.ipynb
examples/scatter_example.ipynb
examples/stacked_bar_example.ipynb
examples/example_datasets/vis1.csv
examples/example_datasets/vis2.csv
examples/example_plots/example1.png
examples/example_plots/example2.png
py_roughviz.egg-info/PKG-INFO
py_roughviz.egg-info/SOURCES.txt
py_roughviz.egg-info/dependency_links.txt
py_roughviz.egg-info/requires.txt
py_roughviz.egg-info/top_level.txt
roughviz/__init__.py
roughviz/charts/__init__.py
roughviz/charts/bar.py
roughviz/charts/barh.py
roughviz/charts/base.py
roughviz/charts/donut.py
roughviz/charts/line.py
roughviz/charts/pie.py
roughviz/charts/scatter.py
roughviz/charts/stacked_bar.py
roughviz/render/__init__.py
roughviz/render/engine.py
roughviz/render/templates/jupyter_notebook.html
tests/test_bar.py
tests/test_barh.py
tests/test_base.py
tests/test_donut.py
tests/test_line.py
tests/test_pie.py
tests/test_scatter.py
tests/test_stacked_bar.py
tests/test_data/vis1.csv
tests/test_data/vis2.csv