Metadata-Version: 2.1
Name: py-roughviz
Version: 0.5.0
Summary: The Python implementation of JavaScript Library RoughViz to create sketchy charts.
Home-page: https://github.com/charlesdong1991/py-roughviz
Author: Kaiqi Dong
Author-email: kaiqidong1991@gmail.com
License: UNKNOWN
Download-URL: https://github.com/charlesdong1991/py-roughviz/archive/v0.5.0.tar.gz
Keywords: py-roughviz,visualization,sketchy charts,hand-drawn charts
Platform: UNKNOWN
Classifier: Development Status :: 3 - Alpha
Classifier: License :: OSI Approved :: MIT License
Classifier: Programming Language :: Python :: 3.6
Classifier: Programming Language :: Python :: 3.7
Classifier: Topic :: Software Development :: Libraries
